Workbook

Sheet retail_orders_raw_dataset
A1: OrderID | B1: OrderDate | C1: CustomerSegment | D1: Region | E1: ProductCategory | F1: Quantity | G1: UnitPrice | H1: DiscountPercent | I1: OrderValue | J1: ShippingCost | K1: PaymentMethod
A2: ORD-1001 | B2: 45619 | C2: Consumer | D2: North | E2: Furniture | F2: 3 | G2: 280.81 | H2: 15 | I2: 716.07 | J2: 4.36 | K2: Cash on Delivery
A3: ORD-1002 | B3: 45336 | C3: Corporate | D3: West | E3: Electronics | F3: 4 | G3: 63.41 | H3: 0 | I3: 253.64 | J3: 13.62 | K3: Credit Card
A4: ORD-1003 | B4: 45579 | C4: Consumer | D4: Central | E4: Apparel | F4: 5 | G4: 44.76 | H4: 20 | I4: 179.04 | J4: 21.99 | K4: Debit Card
A5: ORD-1004 | B5: 45649 | C5: Small Business | D5: East | E5: Furniture | F5: 6 | G5: 207.49 | H5: 0 | I5: 1244.94 | J5: 4.13 | K5: Credit Card
A6: ORD-1005 | B6: 45475 | C6: Small Business | D6: Central | E6: Furniture | F6: 8 | G6: 741.85 | H6: 10 | I6: 5341.32 | J6: 4.87 | K6: UPI
A7: ORD-1006 | B7: 45332 | C7: Corporate | D7: East | E7: Home & Kitchen | F7: 6 | G7: 267.93 | H7: 10 | I7: 1446.82 | J7: 6.42 | K7: Credit Card
A8: ORD-1007 | B8: 45315 | C8: Corporate | D8: South | E8: Furniture | F8: 4 | G8: 887.88 | H8: 20 | I8: 2841.22 | J8: 4.32 | K8: Net Banking
A9: ORD-1008 | B9: 45524 | C9: Corporate | D9: East | E9: Office Supplies | F9: 4 | G9: 25.36 | H9: 15 | I9: 86.22 | J9: 8.14 | K9: Credit Card
A10: ORD-1009 | B10: 45603 | C10: Corporate | D10: South | E10: Home & Kitchen | F10: 3 | G10: 224.16 | H10: 5 | I10: 638.86 | J10: 10.73 | K10: Cash on Delivery
A11: ORD-1010 | B11: 45404 | C11: Corporate | D11: East | E11: Electronics | F11: 1 | G11: 153.07 | H11: 20 | I11: 122.46 | J11: 9.26 | K11: Net Banking
A12: ORD-1011 | B12: 45325 | C12: Consumer | D12: Central | E12: Furniture | F12: 8 | G12: 254.35 | H12: 5 | I12: 1933.06 | J12: 22.35 | K12: UPI
A13: ORD-1012 | B13: 45365 | C13: Small Business | D13: South | E13: Office Supplies | F13: 5 | G13: 45.97 | H13: 15 | I13: 195.37 | J13: 15.45 | K13: Cash on Delivery
... A121: ORD-1120 | B121: 45442 | C121: Small Business | D121: East | E121: Apparel | F121: 7 | G121: 34.65 | H121: 10 | I121: 218.3 | J121: 17.68 | K121: Debit Card

Sheet Data Dictionary
A1: Column Name | B1: Data Type | C1: Description | D1: Example Value
A2: OrderID | B2: Text | C2: Unique identifier for each order | D2: ORD-1001
A3: OrderDate | B3: Date | C3: Date order was placed | D3: 45619
A4: CustomerSegment | B4: Text | C4: Market category of buyer | D4: Consumer
A5: Region | B5: Text | C5: Geographic territory | D5: North
A6: ProductCategory | B6: Text | C6: Product classification | D6: Furniture
A7: Quantity | B7: Integer | C7: Units ordered | D7: 3
A8: UnitPrice | B8: Currency | C8: Price per individual unit | D8: $280.81
A9: DiscountPercent | B9: Integer | C9: Promotional discount rate | D9: 15
A10: OrderValue | B10: Currency | C10: Total billed value after discount | D10: $716.07
A11: ShippingCost | B11: Currency | C11: Logistics cost incurred | D11: $4.36
A12: PaymentMethod | B12: Text | C12: Transaction channel used | D12: Cash on Delivery

Sheet Data_Cleaning
A1: OrderID | B1: OrderDate | C1: CustomerSegment | D1: Region | E1: ProductCategory | F1: Quantity | G1: UnitPrice | H1: DiscountPercent | I1: OrderValue | J1: ShippingCost | K1: PaymentMethod | L1: Duplicate_Check | M1: Blank_Check | N1: Standardize_Text | O1: Math_Check | P1: Validation_Flag | Q1: Cleaning_Log
A2: ORD-1001 | B2: 45619 | C2: Consumer | D2: North | E2: Furniture | F2: 3 | G2: 280.81 | H2: 15 | I2: 716.07 | J2: 4.36 | K2: Cash on Delivery | L2: =IF(COUNTIF($A$2:$A$121, A2)>1, "Duplicate", "OK") -> OK | M2: =IF(COUNTBLANK(A2:K2)>0, "Missing Value", "OK") -> OK | N2: =PROPER(C2) -> Consumer | O2: =ROUND(F2 * G2 * (1 - H2/100), 2) -> 716.07 | P2: =IF(ABS(O2 - I2) > 0.01, "Check", "OK") -> OK | Q2: =IF(AND(L2="OK", M2="OK", P2="OK"), "Clean: No issues", "Review needed") -> Clean: No issues
A3: ORD-1002 | B3: 45336 | C3: Corporate | D3: West | E3: Electronics | F3: 4 | G3: 63.41 | H3: 0 | I3: 253.64 | J3: 13.62 | K3: Credit Card | L3: =IF(COUNTIF($A$2:$A$121, A3)>1, "Duplicate", "OK") -> OK | M3: =IF(COUNTBLANK(A3:K3)>0, "Missing Value", "OK") -> OK | N3: =PROPER(C3) -> Corporate | O3: =ROUND(F3 * G3 * (1 - H3/100), 2) -> 253.64 | P3: =IF(ABS(O3 - I3) > 0.01, "Check", "OK") -> OK | Q3: =IF(AND(L3="OK", M3="OK", P3="OK"), "Clean: No issues", "Review needed") -> Clean: No issues
A4: ORD-1003 | B4: 45579 | C4: Consumer | D4: Central | E4: Apparel | F4: 5 | G4: 44.76 | H4: 20 | I4: 179.04 | J4: 21.99 | K4: Debit Card | L4: =IF(COUNTIF($A$2:$A$121, A4)>1, "Duplicate", "OK") -> OK | M4: =IF(COUNTBLANK(A4:K4)>0, "Missing Value", "OK") -> OK | N4: =PROPER(C4) -> Consumer | O4: =ROUND(F4 * G4 * (1 - H4/100), 2) -> 179.04 | P4: =IF(ABS(O4 - I4) > 0.01, "Check", "OK") -> OK | Q4: =IF(AND(L4="OK", M4="OK", P4="OK"), "Clean: No issues", "Review needed") -> Clean: No issues
A5: ORD-1004 | B5: 45649 | C5: Small Business | D5: East | E5: Furniture | F5: 6 | G5: 207.49 | H5: 0 | I5: 1244.94 | J5: 4.13 | K5: Credit Card | L5: =IF(COUNTIF($A$2:$A$121, A5)>1, "Duplicate", "OK") -> OK | M5: =IF(COUNTBLANK(A5:K5)>0, "Missing Value", "OK") -> OK | N5: =PROPER(C5) -> Small Business | O5: =ROUND(F5 * G5 * (1 - H5/100), 2) -> 1244.94 | P5: =IF(ABS(O5 - I5) > 0.01, "Check", "OK") -> OK | Q5: =IF(AND(L5="OK", M5="OK", P5="OK"), "Clean: No issues", "Review needed") -> Clean: No issues
A6: ORD-1005 | B6: 45475 | C6: Small Business | D6: Central | E6: Furniture | F6: 8 | G6: 741.85 | H6: 10 | I6: 5341.32 | J6: 4.87 | K6: UPI | L6: =IF(COUNTIF($A$2:$A$121, A6)>1, "Duplicate", "OK") -> OK | M6: =IF(COUNTBLANK(A6:K6)>0, "Missing Value", "OK") -> OK | N6: =PROPER(C6) -> Small Business | O6: =ROUND(F6 * G6 * (1 - H6/100), 2) -> 5341.32 | P6: =IF(ABS(O6 - I6) > 0.01, "Check", "OK") -> OK | Q6: =IF(AND(L6="OK", M6="OK", P6="OK"), "Clean: No issues", "Review needed") -> Clean: No issues
A7: ORD-1006 | B7: 45332 | C7: Corporate | D7: East | E7: Home & Kitchen | F7: 6 | G7: 267.93 | H7: 10 | I7: 1446.82 | J7: 6.42 | K7: Credit Card | L7: =IF(COUNTIF($A$2:$A$121, A7)>1, "Duplicate", "OK") -> OK | M7: =IF(COUNTBLANK(A7:K7)>0, "Missing Value", "OK") -> OK | N7: =PROPER(C7) -> Corporate | O7: =ROUND(F7 * G7 * (1 - H7/100), 2) -> 1446.82 | P7: =IF(ABS(O7 - I7) > 0.01, "Check", "OK") -> OK | Q7: =IF(AND(L7="OK", M7="OK", P7="OK"), "Clean: No issues", "Review needed") -> Clean: No issues
A8: ORD-1007 | B8: 45315 | C8: Corporate | D8: South | E8: Furniture | F8: 4 | G8: 887.88 | H8: 20 | I8: 2841.22 | J8: 4.32 | K8: Net Banking | L8: =IF(COUNTIF($A$2:$A$121, A8)>1, "Duplicate", "OK") -> OK | M8: =IF(COUNTBLANK(A8:K8)>0, "Missing Value", "OK") -> OK | N8: =PROPER(C8) -> Corporate | O8: =ROUND(F8 * G8 * (1 - H8/100), 2) -> 2841.22 | P8: =IF(ABS(O8 - I8) > 0.01, "Check", "OK") -> OK | Q8: =IF(AND(L8="OK", M8="OK", P8="OK"), "Clean: No issues", "Review needed") -> Clean: No issues
A9: ORD-1008 | B9: 45524 | C9: Corporate | D9: East | E9: Office Supplies | F9: 4 | G9: 25.36 | H9: 15 | I9: 86.22 | J9: 8.14 | K9: Credit Card | L9: =IF(COUNTIF($A$2:$A$121, A9)>1, "Duplicate", "OK") -> OK | M9: =IF(COUNTBLANK(A9:K9)>0, "Missing Value", "OK") -> OK | N9: =PROPER(C9) -> Corporate | O9: =ROUND(F9 * G9 * (1 - H9/100), 2) -> 86.22 | P9: =IF(ABS(O9 - I9) > 0.01, "Check", "OK") -> OK | Q9: =IF(AND(L9="OK", M9="OK", P9="OK"), "Clean: No issues", "Review needed") -> Clean: No issues
A10: ORD-1009 | B10: 45603 | C10: Corporate | D10: South | E10: Home & Kitchen | F10: 3 | G10: 224.16 | H10: 5 | I10: 638.86 | J10: 10.73 | K10: Cash on Delivery | L10: =IF(COUNTIF($A$2:$A$121, A10)>1, "Duplicate", "OK") -> OK | M10: =IF(COUNTBLANK(A10:K10)>0, "Missing Value", "OK") -> OK | N10: =PROPER(C10) -> Corporate | O10: =ROUND(F10 * G10 * (1 - H10/100), 2) -> 638.86 | P10: =IF(ABS(O10 - I10) > 0.01, "Check", "OK") -> OK | Q10: =IF(AND(L10="OK", M10="OK", P10="OK"), "Clean: No issues", "Review needed") -> Clean: No issues
A11: ORD-1010 | B11: 45404 | C11: Corporate | D11: East | E11: Electronics | F11: 1 | G11: 153.07 | H11: 20 | I11: 122.46 | J11: 9.26 | K11: Net Banking | L11: =IF(COUNTIF($A$2:$A$121, A11)>1, "Duplicate", "OK") -> OK | M11: =IF(COUNTBLANK(A11:K11)>0, "Missing Value", "OK") -> OK | N11: =PROPER(C11) -> Corporate | O11: =ROUND(F11 * G11 * (1 - H11/100), 2) -> 122.46 | P11: =IF(ABS(O11 - I11) > 0.01, "Check", "OK") -> OK | Q11: =IF(AND(L11="OK", M11="OK", P11="OK"), "Clean: No issues", "Review needed") -> Clean: No issues
A12: ORD-1011 | B12: 45325 | C12: Consumer | D12: Central | E12: Furniture | F12: 8 | G12: 254.35 | H12: 5 | I12: 1933.06 | J12: 22.35 | K12: UPI | L12: =IF(COUNTIF($A$2:$A$121, A12)>1, "Duplicate", "OK") -> OK | M12: =IF(COUNTBLANK(A12:K12)>0, "Missing Value", "OK") -> OK | N12: =PROPER(C12) -> Consumer | O12: =ROUND(F12 * G12 * (1 - H12/100), 2) -> 1933.06 | P12: =IF(ABS(O12 - I12) > 0.01, "Check", "OK") -> OK | Q12: =IF(AND(L12="OK", M12="OK", P12="OK"), "Clean: No issues", "Review needed") -> Clean: No issues
A13: ORD-1012 | B13: 45365 | C13: Small Business | D13: South | E13: Office Supplies | F13: 5 | G13: 45.97 | H13: 15 | I13: 195.37 | J13: 15.45 | K13: Cash on Delivery | L13: =IF(COUNTIF($A$2:$A$121, A13)>1, "Duplicate", "OK") -> OK | M13: =IF(COUNTBLANK(A13:K13)>0, "Missing Value", "OK") -> OK | N13: =PROPER(C13) -> Small Business | O13: =ROUND(F13 * G13 * (1 - H13/100), 2) -> 195.37 | P13: =IF(ABS(O13 - I13) > 0.01, "Check", "OK") -> OK | Q13: =IF(AND(L13="OK", M13="OK", P13="OK"), "Clean: No issues", "Review needed") -> Clean: No issues
... A121: ORD-1120 | B121: 45442 | C121: Small Business | D121: East | E121: Apparel | F121: 7 | G121: 34.65 | H121: 10 | I121: 218.3 | J121: 17.68 | K121: Debit Card | L121: =IF(COUNTIF($A$2:$A$121, A121)>1, "Duplicate", "OK") -> OK | M121: =IF(COUNTBLANK(A121:K121)>0, "Missing Value", "OK") -> OK | N121: =PROPER(C121) -> Small Business | O121: =ROUND(F121 * G121 * (1 - H121/100), 2) -> 218.3 | P121: =IF(ABS(O121 - I121) > 0.01, "Check", "OK") -> OK | Q121: =IF(AND(L121="OK", M121="OK", P121="OK"), "Clean: No issues", "Review needed") -> Clean: No issues

Sheet Calculations
A1: OrderID | B1: OrderDate | C1: CustomerSegment | D1: Region | E1: ProductCategory | F1: Quantity | G1: UnitPrice | H1: DiscountPercent | I1: OrderValue | J1: ShippingCost | K1: PaymentMethod | L1: Revenue_Per_Unit | M1: Net_Margin_Proxy | N1: Month | O1: Discount_Tier
A2: ORD-1001 | B2: 45619 | C2: Consumer | D2: North | E2: Furniture | F2: 3 | G2: 280.81 | H2: 15 | I2: 716.07 | J2: 4.36 | K2: Cash on Delivery | L2: =ROUND(I2/F2, 2) -> 238.69 | M2: =ROUND(I2 - J2, 2) -> 711.71 | N2: =TEXT(B2, "mmm") -> Nov | O2: =IF(H2=0, "0%", IF(H2<=5, "5%", IF(H2<=10, "10%", IF(H2<=15, "15%", "20%")))) -> 15%
A3: ORD-1002 | B3: 45336 | C3: Corporate | D3: West | E3: Electronics | F3: 4 | G3: 63.41 | H3: 0 | I3: 253.64 | J3: 13.62 | K3: Credit Card | L3: =ROUND(I3/F3, 2) -> 63.41 | M3: =ROUND(I3 - J3, 2) -> 240.02 | N3: =TEXT(B3, "mmm") -> Feb | O3: =IF(H3=0, "0%", IF(H3<=5, "5%", IF(H3<=10, "10%", IF(H3<=15, "15%", "20%")))) -> 0%
A4: ORD-1003 | B4: 45579 | C4: Consumer | D4: Central | E4: Apparel | F4: 5 | G4: 44.76 | H4: 20 | I4: 179.04 | J4: 21.99 | K4: Debit Card | L4: =ROUND(I4/F4, 2) -> 35.81 | M4: =ROUND(I4 - J4, 2) -> 157.05 | N4: =TEXT(B4, "mmm") -> Oct | O4: =IF(H4=0, "0%", IF(H4<=5, "5%", IF(H4<=10, "10%", IF(H4<=15, "15%", "20%")))) -> 20%
A5: ORD-1004 | B5: 45649 | C5: Small Business | D5: East | E5: Furniture | F5: 6 | G5: 207.49 | H5: 0 | I5: 1244.94 | J5: 4.13 | K5: Credit Card | L5: =ROUND(I5/F5, 2) -> 207.49 | M5: =ROUND(I5 - J5, 2) -> 1240.81 | N5: =TEXT(B5, "mmm") -> Dec | O5: =IF(H5=0, "0%", IF(H5<=5, "5%", IF(H5<=10, "10%", IF(H5<=15, "15%", "20%")))) -> 0%
A6: ORD-1005 | B6: 45475 | C6: Small Business | D6: Central | E6: Furniture | F6: 8 | G6: 741.85 | H6: 10 | I6: 5341.32 | J6: 4.87 | K6: UPI | L6: =ROUND(I6/F6, 2) -> 667.67 | M6: =ROUND(I6 - J6, 2) -> 5336.45 | N6: =TEXT(B6, "mmm") -> Jul | O6: =IF(H6=0, "0%", IF(H6<=5, "5%", IF(H6<=10, "10%", IF(H6<=15, "15%", "20%")))) -> 10%
A7: ORD-1006 | B7: 45332 | C7: Corporate | D7: East | E7: Home & Kitchen | F7: 6 | G7: 267.93 | H7: 10 | I7: 1446.82 | J7: 6.42 | K7: Credit Card | L7: =ROUND(I7/F7, 2) -> 241.14 | M7: =ROUND(I7 - J7, 2) -> 1440.4 | N7: =TEXT(B7, "mmm") -> Feb | O7: =IF(H7=0, "0%", IF(H7<=5, "5%", IF(H7<=10, "10%", IF(H7<=15, "15%", "20%")))) -> 10%
A8: ORD-1007 | B8: 45315 | C8: Corporate | D8: South | E8: Furniture | F8: 4 | G8: 887.88 | H8: 20 | I8: 2841.22 | J8: 4.32 | K8: Net Banking | L8: =ROUND(I8/F8, 2) -> 710.31 | M8: =ROUND(I8 - J8, 2) -> 2836.9 | N8: =TEXT(B8, "mmm") -> Jan | O8: =IF(H8=0, "0%", IF(H8<=5, "5%", IF(H8<=10, "10%", IF(H8<=15, "15%", "20%")))) -> 20%
A9: ORD-1008 | B9: 45524 | C9: Corporate | D9: East | E9: Office Supplies | F9: 4 | G9: 25.36 | H9: 15 | I9: 86.22 | J9: 8.14 | K9: Credit Card | L9: =ROUND(I9/F9, 2) -> 21.56 | M9: =ROUND(I9 - J9, 2) -> 78.08 | N9: =TEXT(B9, "mmm") -> Aug | O9: =IF(H9=0, "0%", IF(H9<=5, "5%", IF(H9<=10, "10%", IF(H9<=15, "15%", "20%")))) -> 15%
A10: ORD-1009 | B10: 45603 | C10: Corporate | D10: South | E10: Home & Kitchen | F10: 3 | G10: 224.16 | H10: 5 | I10: 638.86 | J10: 10.73 | K10: Cash on Delivery | L10: =ROUND(I10/F10, 2) -> 212.95 | M10: =ROUND(I10 - J10, 2) -> 628.13 | N10: =TEXT(B10, "mmm") -> Nov | O10: =IF(H10=0, "0%", IF(H10<=5, "5%", IF(H10<=10, "10%", IF(H10<=15, "15%", "20%")))) -> 5%
A11: ORD-1010 | B11: 45404 | C11: Corporate | D11: East | E11: Electronics | F11: 1 | G11: 153.07 | H11: 20 | I11: 122.46 | J11: 9.26 | K11: Net Banking | L11: =ROUND(I11/F11, 2) -> 122.46 | M11: =ROUND(I11 - J11, 2) -> 113.2 | N11: =TEXT(B11, "mmm") -> Apr | O11: =IF(H11=0, "0%", IF(H11<=5, "5%", IF(H11<=10, "10%", IF(H11<=15, "15%", "20%")))) -> 20%
A12: ORD-1011 | B12: 45325 | C12: Consumer | D12: Central | E12: Furniture | F12: 8 | G12: 254.35 | H12: 5 | I12: 1933.06 | J12: 22.35 | K12: UPI | L12: =ROUND(I12/F12, 2) -> 241.63 | M12: =ROUND(I12 - J12, 2) -> 1910.71 | N12: =TEXT(B12, "mmm") -> Feb | O12: =IF(H12=0, "0%", IF(H12<=5, "5%", IF(H12<=10, "10%", IF(H12<=15, "15%", "20%")))) -> 5%
A13: ORD-1012 | B13: 45365 | C13: Small Business | D13: South | E13: Office Supplies | F13: 5 | G13: 45.97 | H13: 15 | I13: 195.37 | J13: 15.45 | K13: Cash on Delivery | L13: =ROUND(I13/F13, 2) -> 39.07 | M13: =ROUND(I13 - J13, 2) -> 179.92 | N13: =TEXT(B13, "mmm") -> Mar | O13: =IF(H13=0, "0%", IF(H13<=5, "5%", IF(H13<=10, "10%", IF(H13<=15, "15%", "20%")))) -> 15%
... A121: ORD-1120 | B121: 45442 | C121: Small Business | D121: East | E121: Apparel | F121: 7 | G121: 34.65 | H121: 10 | I121: 218.3 | J121: 17.68 | K121: Debit Card | L121: =ROUND(I121/F121, 2) -> 31.19 | M121: =ROUND(I121 - J121, 2) -> 200.62 | N121: =TEXT(B121, "mmm") -> May | O121: =IF(H121=0, "0%", IF(H121<=5, "5%", IF(H121<=10, "10%", IF(H121<=15, "15%", "20%")))) -> 10%
I123: Total Revenue | J123: AVERAGE ORDER VALUE | L123: TOTAL ORDERS | M123: MEDIAN ORDER VALUE
I124: =SUM(I2:I121) -> 106832.85 | J124: =AVERAGE(I2:I121) -> 890.27375 | L124: =COUNT(I2:I121) -> 120 | M124: =MEDIAN(I2:I121) -> 473.335

Sheet Descriptive Statistics
A1: Metric | B1: Formula to Type in Cell C | C1: What Excel Displays | D1: Meaning | E1: Formula to Type in Cell C
A2: Count (Total Orders) | B2: =COUNT(Calculations!I2:I121) -> 120 | C2: 120 | D2: Total number of transactions | E2: =_xlfn.FORMULATEXT(B2) -> =COUNT(Calculations!I2:I121)
A3: Mean (Average) | B3: =AVERAGE(Calculations!I2:I121) -> 890.27375 | C3: $890.27 | D3: The arithmetic average order value | E3: =_xlfn.FORMULATEXT(B3) -> =AVERAGE(Calculations!I2:I121)
A4: Median | B4: =MEDIAN(Calculations!I2:I121) -> 473.335 | C4: $473.33 | D4: Middle order value; 50% are higher, 50% are lower | E4: =_xlfn.FORMULATEXT(B4) -> =MEDIAN(Calculations!I2:I121)
A5: Mode | B5: =IFERROR(_xlfn.MODE.SNGL(Calculations!I2:I121), "All Unique") -> All Unique | C5: All Unique | D5: Most frequent order value (no duplicates in this dataset) | E5: =_xlfn.FORMULATEXT(B5) -> =IFERROR(MODE.SNGL(Calculations!I2:I121), "All Unique")
A6: Minimum | B6: =MIN(Calculations!I2:I121) -> 13.1 | C6: $13.10 | D6: The smallest single order | E6: =_xlfn.FORMULATEXT(B6) -> =MIN(Calculations!I2:I121)
A7: Maximum | B7: =MAX(Calculations!I2:I121) -> 5341.32 | C7: $5,341.32 | D7: The largest single order | E7: =_xlfn.FORMULATEXT(B7) -> =MAX(Calculations!I2:I121)
A8: Range | B8: =MAX(Calculations!$I$2:$I$121) - MIN(Calculations!$I$2:$I$121) -> 5328.22 | C8: $5,328.22 | D8: The total spread between maximum and minimum | E8: =_xlfn.FORMULATEXT(B8) -> =MAX(Calculations!$I$2:$I$121) - MIN(Calculations!$I$2:$I$121)
A9: Sample Variance | B9: =_xlfn.VAR.S(Calculations!I2:I121) -> 1100002 | C9: 1100002 | D9: Statistical variance of order values | E9: =_xlfn.FORMULATEXT(B9) -> =VAR.S(Calculations!I2:I121)
A10: Sample Standard Deviation | B10: =_xlfn.STDEV.S(Calculations!I2:I121) -> 1048.8098 | C10: $1,048.81 | D10: Consistency metric; larger than mean = high variation | E10: =_xlfn.FORMULATEXT(B10) -> =STDEV.S(Calculations!I2:I121)
A11: Q1 (25th Percentile) | B11: =_xlfn.QUARTILE.INC(Calculations!I2:I121, 1) -> 185.695 | C11: $185.69 | D11: 25% of all orders are below this amount | E11: =_xlfn.FORMULATEXT(B11) -> =QUARTILE.INC(Calculations!I2:I121, 1)
A12: Q3 (75th Percentile) | B12: =_xlfn.QUARTILE.INC(Calculations!I2:I121, 3) -> 1280.595 | C12: $1,280.60 | D12: 75% of all orders are below this amount | E12: =_xlfn.FORMULATEXT(B12) -> =QUARTILE.INC(Calculations!I2:I121, 3)
A13: IQR (Interquartile Range) | B13: =B12 - B11 -> 1094.9 | C13: $1,094.90 | D13: The spread of the middle 50% of orders (Q3 minus Q1) | E13: =_xlfn.FORMULATEXT(B13) -> =B12 - B11
A14: Lower Outlier Fence | B14: =B11 - (1.5*B13) -> -1456.655 | C14: -$1,456.66 | D14: Values below this are outliers (none exist) | E14: =_xlfn.FORMULATEXT(B14) -> =B11 - (1.5*B13)
A15: Upper Outlier Fence | B15: =B12+(1.5*B13) -> 2922.945 | C15: $2,922.95 | D15: Values above this are outliers | E15: =_xlfn.FORMULATEXT(B15) -> =B12+(1.5*B13)
A16: Outlier Orders Count | B16: =COUNTIF(Calculations!I2:I121, ">" & B15) -> 8 | C16: 8 | D16: Exactly 8 orders qualify as high-value outliers | E16: =_xlfn.FORMULATEXT(B16) -> =COUNTIF(Calculations!I2:I121, ">" & B15)
A17: 90th Percentile | B17: =_xlfn.PERCENTILE.INC(Calculations!I2:I121, 0.9) -> 2426.08 | C17: $2,426.08 | D17: Top 10% threshold (useful for VIP loyalty tiering) | E17: =_xlfn.FORMULATEXT(B17) -> =PERCENTILE.INC(Calculations!I2:I121, 0.9)
A19: Region | B19: Total Revenue | C19: Average Order Value | D19: Order Count | E19: Total Revenue
A20: Central | B20: =SUMIF(Calculations!$D$2:$D$121, A20, Calculations!$I$2:$I$121) -> 34125.63 | C20: =AVERAGEIF(Calculations!$D$2:$D$121, "Central", Calculations!$I$2:$I$121) -> 1066.4259 | D20: =COUNTIF(Calculations!$D$2:$D$121, "Central") -> 32 | E20: =SUMIF(Calculations!$D$2:$D$121, "Central", Calculations!$I$2:$I$121) -> 34125.63
A21: East | B21: =SUMIF(Calculations!$D$2:$D$121, "East", Calculations!$I$2:$I$121) -> 24833.11 | C21: =AVERAGEIF(Calculations!$D$2:$D$121, "East", Calculations!$I$2:$I$121) -> 827.77033 | D21: =COUNTIF(Calculations!$D$2:$D$121, "East") -> 30 | E21: =SUMIF(Calculations!$D$2:$D$121, "East", Calculations!$I$2:$I$121) -> 24833.11
A22: South | B22: =SUMIF(Calculations!$D$2:$D$121, "South", Calculations!$I$2:$I$121) -> 21448.01 | C22: =AVERAGEIF(Calculations!$D$2:$D$121, "South", Calculations!$I$2:$I$121) -> 974.90955 | D22: =COUNTIF(Calculations!$D$2:$D$121, "South") -> 22 | E22: =SUMIF(Calculations!$D$2:$D$121, "South", Calculations!$I$2:$I$121) -> 21448.01
A23: West | B23: =SUMIF(Calculations!$D$2:$D$121, "West", Calculations!$I$2:$I$121) -> 13759 | C23: =AVERAGEIF(Calculations!$D$2:$D$121, "West", Calculations!$I$2:$I$121) -> 687.95 | D23: =COUNTIF(Calculations!$D$2:$D$121, "West") -> 20 | E23: =SUMIF(Calculations!$D$2:$D$121, "West", Calculations!$I$2:$I$121) -> 13759
A24: North | B24: =SUMIF(Calculations!$D$2:$D$121, "North", Calculations!$I$2:$I$121) -> 12667.1 | C24: =AVERAGEIF(Calculations!$D$2:$D$121, "North", Calculations!$I$2:$I$121) -> 791.69375 | D24: =COUNTIF(Calculations!$D$2:$D$121, "North") -> 16 | E24: =SUMIF(Calculations!$D$2:$D$121, "North", Calculations!$I$2:$I$121) -> 12667.1
A26: Customer Segment | B26: Total Revenue | C26: Average Order Value | D26: Order Count | E26: Total Revenue
A27: Corporate | B27: =SUMIF(Calculations!$C$2:$C$121, "Corporate", Calculations!$I$2:$I$121) -> 41726.44 | C27: =AVERAGEIF(Calculations!$C$2:$C$121, "Corporate", Calculations!$I$2:$I$121) -> 1098.0642 | D27: =COUNTIF(Calculations!$C$2:$C$121, "Corporate") -> 38 | E27: =SUMIF(Calculations!$C$2:$C$121, "Corporate", Calculations!$I$2:$I$121) -> 41726.44
A28: Consuner | B28: =SUMIF(Calculations!$C$2:$C$121, "Consumer", Calculations!$I$2:$I$121) -> 29127.07 | C28: =AVERAGEIF(Calculations!$C$2:$C$121, "Consumer", Calculations!$I$2:$I$121) -> 832.202 | D28: =COUNTIF(Calculations!$C$2:$C$121, "Consumer") -> 35 | E28: =SUMIF(Calculations!$C$2:$C$121, "Consumer", Calculations!$I$2:$I$121) -> 29127.07
A29: Small Bussiness | B29: =SUMIF(Calculations!$C$2:$C$121, "Small Business", Calculations!$I$2:$I$121) -> 35979.34 | C29: =AVERAGEIF(Calculations!$C$2:$C$121, "Small Business", Calculations!$I$2:$I$121) -> 765.51787 | D29: =COUNTIF(Calculations!$C$2:$C$121, "Small Business") -> 47 | E29: =SUMIF(Calculations!$C$2:$C$121, "Small Business", Calculations!$I$2:$I$121) -> 35979.34

Sheet Statistical_Analysis
A1: Retail Orders — Key Statistical Findings & Insights
A3: (Central Tendency & Skew) :-Right-Skewed Distribution: The average order value ($890.27) is nearly double the median ($473.33). This large gap indicates a strong right-skew, meaning a small number of very large orders inflate the average, while the typical customer basket is closer to $473.
A4: (Consistency & Volatility):High Size Inconsistency: The sample standard deviation ($1,048.81) exceeds the mean ($890.27). This shows extreme variability in customer basket sizes, ranging from small $13.10 purchases to over $5,000 bulk orders.
A5: (Typical Range & IQR):Middle 50% Spread: The typical middle 50% of orders (interquartile range) spans from $185.69 (Q1) to $1,280.60 (Q3), with an IQR of $1,094.90.
A6: (Outlier Analysis):-High-Value Outliers: There are 8 outlier orders exceeding the upper statistical boundary of $2,922.95. All 8 are high-quantity purchases (6–8 units) of Furniture and Electronics with little to no discount.
A7: (Volume vs. Revenue Contrast): Frequency vs. Value Paradox: Office Supplies is the most frequently ordered category (31 orders; 25.8% of volume), but accounts for less than 4% of total revenue. Conversely, Furniture accounts for 19.2% of orders but drives 44.5% of total revenue.
A8: (Regional Performance): Top Revenue Region: Central is the leading territory, generating $34,125.63 (31.9% of company revenue) with the highest Average Order Value ($1,066.43 across 32 orders).
A9: (Customer Segments): Highest-Value Segment: Corporate clients yield the highest Average Order Value at $1,098.06, compared to $832.20 for Consumers and $765.52 for Small Businesses.
A10: (Loyalty & VIP Threshold): VIP Program Design: The 90th percentile is $2,426.08. Only 10% of orders reach or exceed this level, making ~$2,500 an effective threshold for an elite customer tier.

Sheet Pivot Table
A1: Row Labels | B1: Sum of OrderValue | C1: Average Order Value | D1: Order Count
A2: Central | B2: 34125.63 | C2: 1066.4259 | D2: 32
A3: East | B3: 24833.11 | C3: 827.77033 | D3: 30
A4: North | B4: 12667.1 | C4: 791.69375 | D4: 16
A5: South | B5: 21448.01 | C5: 974.90955 | D5: 22
A6: West | B6: 13759 | C6: 687.95 | D6: 20
A7: Grand Total | B7: 106832.85 | C7: 890.27375 | D7: 120
A9: Sum of OrderValue | B9: Column Labels
A10: Row Labels | B10: Consumer | C10: Corporate | D10: Small Business | E10: Grand Total
A11: Apparel | B11: 1676.06 | C11: 2169.64 | D11: 5065.19 | E11: 8910.89
A12: Electronics | B12: 11082.21 | C12: 13725.42 | D12: 6631.23 | E12: 31438.86
A13: Furniture | B13: 11744.61 | C13: 15998.12 | D13: 19802.39 | E13: 47545.12
A14: Home & Kitchen | B14: 3456.66 | C14: 8514.51 | D14: 2817.14 | E14: 14788.31
A15: Office Supplies | B15: 1167.53 | C15: 1318.75 | D15: 1663.39 | E15: 4149.67
A16: Grand Total | B16: 29127.07 | C16: 41726.44 | D16: 35979.34 | E16: 106832.85
A18: Row Labels | B18: Count of OrderID | C18: Count of OrderID2
A19: Cash on Delivery | B19: 26 | C19: 0.21666667
A20: Credit Card | B20: 23 | C20: 0.19166667
A21: Debit Card | B21: 20 | C21: 0.16666667
A22: Net Banking | B22: 21 | C22: 0.175
A23: UPI | B23: 30 | C23: 0.25
A24: Grand Total | B24: 120 | C24: 1

Sheet Dashboard
B1: Retail Sales & Performance Dashboard
M29: Executive Statistical Strategy — Key Points Core Insights Severe right-skew: Average order $890 vs median $473. A few large orders inflate the average. Discount paradox: Undiscounted AOV $1,083 vs discounted AOV $689. Discounts are not increasing basket size. 5 Immediate Strategic Moves 1. Replace blanket discounts: Use spend thresholds like $600 free delivery or $1,500 save $150. 2. Prioritize Corporate & Central: Corporate AOV $1,098. Central generates 32% of revenue ($34,126). 3. Bundle Office Supplies: Cross-sell with Furniture and Tech instead of standalone marketing. 4. Cap COD at $500: Require UPI/Card prepayment for higher-value orders. 5. Launch $2,500 VIP Tier: Target the top 10% of high-value buyers.
